synthetic_graph_benchmarks/__init__.py
synthetic_graph_benchmarks/benchmarks.py
synthetic_graph_benchmarks/dataset.py
synthetic_graph_benchmarks/dist_helper.py
synthetic_graph_benchmarks/spectre_utils.py
synthetic_graph_benchmarks/utils.py
synthetic_graph_benchmarks-0.1.2.dist-info/METADATA
synthetic_graph_benchmarks-0.1.2.dist-info/WHEEL
synthetic_graph_benchmarks-0.1.2.dist-info/entry_points.txt
synthetic_graph_benchmarks-0.1.2.dist-info/licenses/LICENSE
synthetic_graph_benchmarks-0.1.2.dist-info/RECORD
