Metadata-Version: 2.4
Name: synthetic-graph-benchmarks
Version: 0.1.2
Summary: Standardized benchmarks for evaluating synthetic graph generation methods
Project-URL: Homepage, https://github.com/peteole/synthetic_graph_benchmarks
Project-URL: Repository, https://github.com/peteole/synthetic_graph_benchmarks
Project-URL: Documentation, https://github.com/peteole/synthetic_graph_benchmarks#readme
Project-URL: Bug Tracker, https://github.com/peteole/synthetic_graph_benchmarks/issues
Author-email: Ole Petersen <peteole2707@gmail.com>
Maintainer-email: Ole Petersen <peteole2707@gmail.com>
License: MIT
License-File: LICENSE
Keywords: benchmarks,evaluation-metrics,graph-generation,graph-neural-networks,machine-learning,networkx,synthetic-graphs
Classifier: Development Status :: 4 - Beta
Classifier: Intended Audience :: Developers
Classifier: Intended Audience :: Science/Research
Classifier: License :: OSI Approved :: MIT License
Classifier: Operating System :: OS Independent
Classifier: Programming Language :: Python :: 3
Classifier: Programming Language :: Python :: 3.10
Classifier: Programming Language :: Python :: 3.11
Classifier: Programming Language :: Python :: 3.12
Classifier: Topic :: Scientific/Engineering :: Artificial Intelligence
Classifier: Topic :: Scientific/Engineering :: Mathematics
Classifier: Topic :: Software Development :: Libraries :: Python Modules
Requires-Python: >=3.10
Requires-Dist: networkx>=3.4.2
Requires-Dist: numpy>=2.2.6
Requires-Dist: orca-graphlets>=0.1.4
Requires-Dist: pygsp>=0.5.1
Requires-Dist: requests>=2.32.4
Requires-Dist: scikit-learn>=1.7.1
Requires-Dist: scipy>=1.15.3
Requires-Dist: torch>=2.3.0
